setup.py
bin/importer
importer/__init__.py
importer/__main__.py
importer/mix.py
importer/tz.py
importer.egg-info/PKG-INFO
importer.egg-info/SOURCES.txt
importer.egg-info/dependency_links.txt
importer.egg-info/requires.txt
importer.egg-info/top_level.txt
importer/lib/mixpanel/__init__.py
importer/lib/mixpanel/mixpanel.py
importer_tests/__init__.py
importer_tests/__main__.py
importer_tests/runner.py
importer_tests/test_keen.py
importer_tests/test_mix.py
importer_tests/test_mixpanel.py
importer_tests/test_tz.py