Metadata-Version: 1.0
Name: importer
Version: 1.1
Summary: Data transfer tool for analytics providers
Home-page: https://github.com/keenlabs/Keen-Importer
Author: Sam Gammon
Author-email: sam@keen.io
License: UNKNOWN
Platform: UNKNOWN
